maui/__init__.py
maui/_version.py
maui/autoencoders_architectures.py
maui/maui_warnings.py
maui/model.py
maui/utils.py
maui_tools-0.1.95.dist-info/LICENSE
maui_tools-0.1.95.dist-info/METADATA
maui_tools-0.1.95.dist-info/WHEEL
maui_tools-0.1.95.dist-info/top_level.txt
maui_tools-0.1.95.dist-info/RECORD
