Metadata-Version: 2.1
Name: maui-tools
Version: 0.1.95
Summary: Multi-omics Autoencoder Integration
Home-page: https://github.com/BIMSBbioinfo/maui
Author: Jonathan Ronen
Author-email: yablee@gmail.com
License: GPLv3
Platform: UNKNOWN
Requires-Dist: pytest
Requires-Dist: numpy (>=1.18.2)
Requires-Dist: pandas (>=1.0.3)
Requires-Dist: scipy (==1.2.1)
Requires-Dist: scikit-learn
Requires-Dist: keras
Requires-Dist: tensorflow (<2.0)
Requires-Dist: pytest (>=3.6.0)
